{
  "frames": {
    "0.png": {
      "frame": {
        "x": 0,
        "y": 0,
        "w": 43,
        "h": 52
      },
      "rotated": false,
      "trimmed": false,
      "spriteSourceSize": {
        "x": 0,
        "y": 0,
        "w": 43,
        "h": 52
      },
      "sourceSize": {
        "w": 43,
        "h": 52
      },
      "pivot": {
        "x": 0.5,
        "y": 0.5
      }
    },
    "4.png": {
      "frame": {
        "x": 43,
        "y": 0,
        "w": 43,
        "h": 52
      },
      "rotated": false,
      "trimmed": false,
      "spriteSourceSize": {
        "x": 0,
        "y": 0,
        "w": 43,
        "h": 52
      },
      "sourceSize": {
        "w": 43,
        "h": 52
      },
      "pivot": {
        "x": 0.5,
        "y": 0.5
      }
    },
    "3.png": {
      "frame": {
        "x": 0,
        "y": 52,
        "w": 36,
        "h": 46
      },
      "rotated": false,
      "trimmed": true,
      "spriteSourceSize": {
        "x": 3,
        "y": 2,
        "w": 36,
        "h": 46
      },
      "sourceSize": {
        "w": 43,
        "h": 52
      },
      "pivot": {
        "x": 0.5,
        "y": 0.5
      }
    },
    "2.png": {
      "frame": {
        "x": 36,
        "y": 52,
        "w": 18,
        "h": 40
      },
      "rotated": false,
      "trimmed": true,
      "spriteSourceSize": {
        "x": 14,
        "y": 4,
        "w": 18,
        "h": 40
      },
      "sourceSize": {
        "w": 43,
        "h": 52
      },
      "pivot": {
        "x": 0.5,
        "y": 0.5
      }
    },
    "1.png": {
      "frame": {
        "x": 54,
        "y": 52,
        "w": 9,
        "h": 9
      },
      "rotated": false,
      "trimmed": true,
      "spriteSourceSize": {
        "x": 18,
        "y": 18,
        "w": 9,
        "h": 9
      },
      "sourceSize": {
        "w": 43,
        "h": 52
      },
      "pivot": {
        "x": 0.5,
        "y": 0.5
      }
    },
    "5.png": {
      "frame": {
        "x": 0,
        "y": 0,
        "w": 43,
        "h": 52
      },
      "rotated": false,
      "trimmed": false,
      "spriteSourceSize": {
        "x": 0,
        "y": 0,
        "w": 43,
        "h": 52
      },
      "sourceSize": {
        "w": 43,
        "h": 52
      },
      "pivot": {
        "x": 0.5,
        "y": 0.5
      }
    }
  },
  "meta": {
    "app": "http://free-tex-packer.com",
    "version": "0.6.6",
    "image": "slash-hit.png",
    "format": "RGBA8888",
    "size": {
      "w": 86,
      "h": 98
    },
    "scale": 1
  }
}
